gitflow_manager/__init__.py
gitflow_manager/changelog.py
gitflow_manager/errors.py
gitflow_manager/file_utils.py
gitflow_manager/git_hosts.py
gitflow_manager/gitflow_manager.py
gitflow_manager/run.py
gitflow_manager/start.py
gitflow_manager-1.1.3.dist-info/METADATA
gitflow_manager-1.1.3.dist-info/WHEEL
gitflow_manager-1.1.3.dist-info/entry_points.txt
gitflow_manager-1.1.3.dist-info/top_level.txt
gitflow_manager-1.1.3.dist-info/RECORD
