Metadata-Version: 2.4
Name: gitflow_manager
Version: 1.1.3
Summary: This package contains the Anacision Git Manager.
Requires-Python: >=3.10
Requires-Dist: gitpython>=3.1.24
Requires-Dist: pystache>=0.6.0
Requires-Dist: requests>=2.27.1
Requires-Dist: tomlkit>=0.13.3
